LICENSE
README.md
requirements.txt
setup.py
ShellcodeTester.egg-info/PKG-INFO
ShellcodeTester.egg-info/SOURCES.txt
ShellcodeTester.egg-info/dependency_links.txt
ShellcodeTester.egg-info/entry_points.txt
ShellcodeTester.egg-info/not-zip-safe
ShellcodeTester.egg-info/requires.txt
ShellcodeTester.egg-info/top_level.txt
nasmshell/__init__.py
nasmshell/__main__.py
nasmshell/args.py
nasmshell/config.py
nasmshell/nasmshell.py
nasmshell/libs/__init__.py
nasmshell/libs/cmd.py
shell_bins/__init__.py
shell_bins/linux/__init__.py
shell_bins/linux/nasm
shell_bins/linux/objdump
shell_bins/macosx/__init__.py
shell_bins/macosx/nasm
shell_bins/macosx/objdump
shell_bins/windows/__init__.py
shell_bins/windows/nasm.exe
shell_bins/windows/objdump.exe
shell_libs/__init__.py
shell_libs/__meta__.py
shell_libs/asmfile.py
shell_libs/assembler.py
shell_libs/color.py
shell_libs/compiler.py
shell_libs/disassembler.py
shell_libs/inlineassembler.py
shell_libs/logger.py
shell_libs/process.py
shell_libs/runner.py
shell_libs/tools.py
shell_libs/transform.py
shellcodetester/__init__.py
shellcodetester/__main__.py
shellcodetester/args.py
shellcodetester/config.py
shellcodetester/password.py
shellcodetester/shellcodetester.py
tests/__init__.py
tests/tests.py